[
  {
    "id": "ch01-tong-quan",
    "name": "I. Tổng quan cấu tạo cơ thể",
    "description": "Trang 1–10 · Cấp độ, tế bào, mô, tư thế, mặt phẳng",
    "pageRange": [
      1,
      10
    ],
    "conceptIds": [
      "cap-hoa-hoc",
      "nguyen-tu",
      "phan-tu",
      "cap-te-bao",
      "te-bao",
      "te-bao-hong-cau",
      "te-bao-than-kinh",
      "te-bao-bieu-mo",
      "te-bao-co-tron",
      "cap-mo",
      "mo-bieu-mo",
      "mo-lien-ket",
      "mo-co",
      "mo-than-kinh",
      "co-quan",
      "he-co-quan",
      "co-the",
      "tu-the-giai-phau",
      "phia-tren",
      "phia-duoi",
      "phia-truoc",
      "phia-sau",
      "ben-trai",
      "ben-phai",
      "mp-nam-ngang",
      "hanh-dong-xoay",
      "mp-dung-ngang",
      "hanh-dong-giang",
      "hanh-dong-khep",
      "hanh-dong-nghieng",
      "mp-dung-doc",
      "hanh-dong-gap",
      "hanh-dong-duoi",
      "gan",
      "sun",
      "mo-mo"
    ],
    "diagramIds": []
  },
  {
    "id": "ch02-xuong",
    "name": "II. Cấu tạo & chức năng xương",
    "description": "Trang 11–13, 48 · Phân loại, chức năng, xương, đốt sống",
    "pageRange": [
      11,
      13
    ],
    "conceptIds": [
      "206-xuong",
      "xuong-truc",
      "xuong-treo",
      "xuong-vun",
      "xuong-dai",
      "xuong-ngan",
      "xuong-det",
      "xuong-bat-dinh",
      "xuong-vung",
      "xn-nang-do",
      "xn-van-dong",
      "xn-san-xuat-mau",
      "xn-du-tru",
      "xuong-so",
      "xuong-ham-duoi",
      "cot-song",
      "dot-song-co",
      "dot-song-nguc",
      "dot-song-lung",
      "xuong-cung",
      "xuong-cut",
      "xuong-do",
      "xuong-uc",
      "xuong-suon",
      "xuong-bai-vai",
      "xuong-canh-tay",
      "xuong-quay",
      "xuong-tru",
      "xuong-chau",
      "xuong-dui",
      "xuong-banh-che",
      "xuong-chay",
      "xuong-mac",
      "than-dot-song",
      "cung-dot-song",
      "mom-gai",
      "mom-ngang",
      "lo-song",
      "chuc-nang-dot-song",
      "27-xuong-ban-tay",
      "xuong-co-tay",
      "xuong-ban-tay",
      "xuong-doi-ngon"
    ],
    "diagramIds": []
  },
  {
    "id": "ch03-khop",
    "name": "III. Hệ thống khớp",
    "description": "Trang 14–24 · Phân loại, 6 loại khớp, ROM",
    "pageRange": [
      14,
      24
    ],
    "conceptIds": [
      "khop-dinh-nghia",
      "khop-dong",
      "khop-ban-dong",
      "khop-bat-dong",
      "khop-hoat-dich",
      "sun-khop",
      "day-chang",
      "mang-hoat-dich",
      "khoang-hoat-dich",
      "dich-khop",
      "khop-truc",
      "khop-ban-le",
      "khop-yen-ngua",
      "khop-truot",
      "khop-loi-cau",
      "khop-o-cau",
      "c1-atlas",
      "c2-axis",
      "khop-quay-tru",
      "khop-khuyu",
      "khop-goi",
      "khop-ngon-cai",
      "facet-joint",
      "khop-co-tay",
      "khop-hong",
      "khop-vai",
      "rom-dinh-nghia",
      "rom-vai-gap",
      "rom-vai-duoi",
      "rom-cot-gap",
      "rom-cot-duoi",
      "rom-cot-nghieng",
      "rom-goi-gap",
      "khop-canh-tay-tru",
      "khop-canh-tay-quay",
      "khop-quay-tru-gan",
      "tennis-elbow",
      "golfer-elbow",
      "day-chang-dinh-nghia",
      "day-chang-vs-gan",
      "acl",
      "lcl",
      "day-chang-mom-ngang"
    ],
    "diagramIds": []
  },
  {
    "id": "ch04-van-dong",
    "name": "IV. Phạm vi chuyển động",
    "description": "Trang 25–31 · AROM, PROM, ROM cột sống & hông",
    "pageRange": [
      25,
      31
    ],
    "conceptIds": [
      "arom",
      "prom",
      "rom-linh-hoat",
      "rom-on-dinh",
      "rom-cs-gap-co",
      "rom-cs-gap-nguc",
      "rom-cs-gap-lung",
      "rom-cs-duoi-co",
      "rom-cs-duoi-nguc",
      "rom-cs-duoi-lung",
      "rom-cs-nghieng-co",
      "rom-cs-nghieng-nguc",
      "rom-cs-nghieng-lung",
      "rom-cs-xoay-co",
      "rom-cs-xoay-nguc",
      "rom-cs-xoay-lung",
      "rom-hong-gap",
      "rom-hong-duoi",
      "rom-hong-dang",
      "rom-hong-khep",
      "rom-hong-xoay-ngoai",
      "rom-hong-xoay-trong"
    ],
    "diagramIds": []
  },
  {
    "id": "ch05-mac-co",
    "name": "V. Mạc cơ & chóp xoay",
    "description": "Trang 32–50 · Fascia, rotator cuff",
    "pageRange": [
      32,
      50
    ],
    "conceptIds": [
      "mac-co",
      "mac-nguc-that-lung",
      "rotator-cuff",
      "co-duoi-vai",
      "co-tren-gai",
      "co-duoi-gai",
      "co-tron-be",
      "chop-xoay-y-nghia",
      "co-tim",
      "co-xuong",
      "co-tron",
      "co-dong-tam",
      "co-ly-tam",
      "co-dang-truong"
    ],
    "diagramIds": []
  },
  {
    "id": "ch06-dia-dem",
    "name": "VI. Đĩa đệm & Pilates",
    "description": "Trang 51–53 · Thoát vị, thoái hóa, động tác tránh",
    "pageRange": [
      51,
      53
    ],
    "conceptIds": [
      "dia-dem",
      "nhan-nhay",
      "vong-soi",
      "thoat-vi-dia-dem",
      "dia-dem-binh-thuong",
      "khoi-thoat-vi",
      "tranh-gap-sau",
      "tranh-xoay",
      "tranh-gap-xoay",
      "tranh-nang-2-chan",
      "tranh-uan-qua",
      "thoai-hoa-dia-dem",
      "loi-dia-dem",
      "hep-dia-dem",
      "gai-xuong",
      "cot-song-quan-trong",
      "gu-lung",
      "cong-veo",
      "truot-dot-song",
      "piriformis",
      "co-vai-gay"
    ],
    "diagramIds": []
  },
  {
    "id": "ch07-chi-tren",
    "name": "VII. Cơ chi trên",
    "description": "Trang 54–58 · 15 cơ — nguyên ủy, bám, hành động",
    "pageRange": [
      54,
      58
    ],
    "conceptIds": [
      "co-delta",
      "co-nhi-dau",
      "co-tam-dau",
      "co-canh-tay-truoc",
      "co-ngua",
      "co-sap-tron",
      "co-gap-co-quay",
      "co-duoi-co-quay",
      "co-nguc-lon",
      "co-lung-rong",
      "co-tren-gai-ct",
      "co-duoi-gai-ct",
      "co-tron-be-ct",
      "co-duoi-vai-ct",
      "co-qua-canh-tay"
    ],
    "diagramIds": []
  },
  {
    "id": "ch08-phan-than",
    "name": "VIII. Phần thân & core",
    "description": "Trang 59–62 · Cơ bụng, cơ lưng",
    "pageRange": [
      59,
      62
    ],
    "conceptIds": [
      "phan-than",
      "long-nguc",
      "o-bung-chau",
      "trung-tam-tu-the",
      "truyen-luc-phan-than",
      "co-thang-bung",
      "co-cheo-ngoai",
      "co-cheo-trong",
      "co-ngang-bung",
      "co-thang",
      "co-lung-rong-pt",
      "co-nang-vai",
      "co-tram",
      "co-vuong-that-lung",
      "co-dung-song",
      "co-da-nhanh"
    ],
    "diagramIds": []
  },
  {
    "id": "ch09-khung-chau",
    "name": "IX. Khung chậu",
    "description": "Trang 63–66 · Cấu trúc, chuyển động, sai lệch",
    "pageRange": [
      63,
      66
    ],
    "conceptIds": [
      "khung-chau",
      "mao-chau",
      "eo-tren",
      "khop-hong-kc",
      "gai-lu-ngoi",
      "u-ngoi",
      "xuong-mu",
      "khop-mu",
      "chong-do-trong-luong",
      "bao-ve-noi-tang",
      "gam-co-chau",
      "co-san-chau",
      "co-that-lung-chau",
      "asis",
      "kc-trung-tinh",
      "kc-nga-truoc",
      "kc-nga-sau",
      "kc-lech-ben",
      "kc-xoay-van",
      "sl-nga-truoc",
      "sl-nga-sau",
      "sl-lech-ben",
      "sl-xoay"
    ],
    "diagramIds": []
  }
]